reverse_engineering_assistant/.gitignore
reverse_engineering_assistant/__init__.py
reverse_engineering_assistant/assistant.py
reverse_engineering_assistant/assistant_api_server.py
reverse_engineering_assistant/chat_client.py
reverse_engineering_assistant/crash_dump.py
reverse_engineering_assistant/documents.py
reverse_engineering_assistant/model.py
reverse_engineering_assistant/reva_exceptions.py
reverse_engineering_assistant/tool.py
reverse_engineering_assistant/api_server_tools/__init__.py
reverse_engineering_assistant/api_server_tools/connection.py
reverse_engineering_assistant/api_server_tools/llm_tools.py
reverse_engineering_assistant/api_server_tools/re_tools.py
reverse_engineering_assistant/api_server_tools/re_tool_box/__init__.py
reverse_engineering_assistant/api_server_tools/re_tool_box/bookmarks.py
reverse_engineering_assistant/api_server_tools/re_tool_box/comment.py
reverse_engineering_assistant/api_server_tools/re_tool_box/cross_reference.py
reverse_engineering_assistant/api_server_tools/re_tool_box/cursor.py
reverse_engineering_assistant/api_server_tools/re_tool_box/data.py
reverse_engineering_assistant/api_server_tools/re_tool_box/decompilation.py
reverse_engineering_assistant/api_server_tools/re_tool_box/symbols.py
reverse_engineering_assistant/protocol/RevaBookmark_pb2.py
reverse_engineering_assistant/protocol/RevaBookmark_pb2.pyi
reverse_engineering_assistant/protocol/RevaBookmark_pb2_grpc.py
reverse_engineering_assistant/protocol/RevaChat_pb2.py
reverse_engineering_assistant/protocol/RevaChat_pb2.pyi
reverse_engineering_assistant/protocol/RevaChat_pb2_grpc.py
reverse_engineering_assistant/protocol/RevaComment_pb2.py
reverse_engineering_assistant/protocol/RevaComment_pb2.pyi
reverse_engineering_assistant/protocol/RevaComment_pb2_grpc.py
reverse_engineering_assistant/protocol/RevaData_pb2.py
reverse_engineering_assistant/protocol/RevaData_pb2.pyi
reverse_engineering_assistant/protocol/RevaData_pb2_grpc.py
reverse_engineering_assistant-2.9.4.dist-info/METADATA
reverse_engineering_assistant-2.9.4.dist-info/WHEEL
reverse_engineering_assistant-2.9.4.dist-info/entry_points.txt
reverse_engineering_assistant-2.9.4.dist-info/top_level.txt
reverse_engineering_assistant-2.9.4.dist-info/RECORD
