Metadata-Version: 2.1
Name: reverse-engineering-assistant
Version: 2.9.4
Summary: An AI assistant for reverse engineering tasks
Author: サイバーカイダ (cyberkaida)
Classifier: License :: OSI Approved :: Apache Software License
Classifier: Natural Language :: English
Classifier: Operating System :: OS Independent
Classifier: Programming Language :: Python
Requires-Dist: langchain
Requires-Dist: langchain-core
Requires-Dist: langchain-openai
Requires-Dist: langchain-community
Requires-Dist: langchain-experimental
Requires-Dist: langgraph
Requires-Dist: prompt-toolkit
Requires-Dist: sentence-transformers
Requires-Dist: PyYAML
Requires-Dist: pydantic
Requires-Dist: rich
Requires-Dist: grpcio
Requires-Dist: protobuf
Requires-Dist: flask
